interposer/__init__.py
interposer/example/weather.py
interposer/py.typed
interposer/recorder.py
interposer/tapedeck.py
interposer-1.0.0.dist-info/LICENSE
interposer-1.0.0.dist-info/WHEEL
interposer-1.0.0.dist-info/METADATA
interposer-1.0.0.dist-info/RECORD
