Metadata-Version: 2.1
Name: interposer
Version: 1.0.0
Summary: A generic call intercept wrapper for call inspection, modification, permission checking, recording, and playback.
Home-page: https://github.com/cloudtruth/interposer/
License: Apache-2.0
Keywords: testing,record,playback,redact,inject,security,intercept,interpose,wrap
Author: James E. King III
Author-email: jking@apache.org
Requires-Python: >=3.7,<3.11
Classifier: Development Status :: 4 - Beta
Classifier: Intended Audience :: Developers
Classifier: License :: OSI Approved :: Apache Software License
Classifier: Programming Language :: Python :: 3
Classifier: Programming Language :: Python :: 3 :: Only
Classifier: Programming Language :: Python :: 3.10
Classifier: Programming Language :: Python :: 3.7
Classifier: Programming Language :: Python :: 3.8
Classifier: Programming Language :: Python :: 3.9
Classifier: Topic :: Software Development :: Libraries :: Python Modules
Classifier: Typing :: Typed
Requires-Dist: pyyaml (>=6.0,<7.0)
Requires-Dist: wrapt (>=1.13.3,<2.0.0)
Project-URL: Repository, https://github.com/cloudtruth/interposer/
